snake_game/__init__.py
snake_game/game.py
snake_game/assets/sounds/som_comer.wav
snake_game/assets/sounds/som_fim_jogo.wav
snake_game/assets/sounds/som_fundo.wav
snake_game/assets/sounds/som_passo.wav
snake_game_package_dio-1.0.2.dist-info/METADATA
snake_game_package_dio-1.0.2.dist-info/WHEEL
snake_game_package_dio-1.0.2.dist-info/entry_points.txt
snake_game_package_dio-1.0.2.dist-info/top_level.txt
snake_game_package_dio-1.0.2.dist-info/RECORD
