Metadata-Version: 2.4
Name: snake_game_package_dio
Version: 1.0.2
Summary: O clássico jogo da Cobrinha foi recriado em estilo Synthwave Cyberpunk.
Home-page: https://github.com/skynetsites/snake_game_package
Author: Isaias Oliveira
Author-email: isaiaswebnet@gmail.com
Requires-Python: >=3.8
Requires-Dist: pygame>=2.0.0
Dynamic: author
Dynamic: author-email
Dynamic: description
Dynamic: description-content-type
Dynamic: home-page
Dynamic: requires-dist
Dynamic: requires-python
Dynamic: summary
